hcai_models/__init__.py
hcai_models/core/__init__.py
hcai_models/core/abstract_audio_model.py
hcai_models/core/abstract_image_model.py
hcai_models/core/abstract_model.py
hcai_models/core/abstract_multi_input_model.py
hcai_models/core/abstract_multi_output_model.py
hcai_models/core/builder.py
hcai_models/core/keras_model.py
hcai_models/core/pytorch_model.py
hcai_models/core/registered_model.py
hcai_models/core/ssi_compat.py
hcai_models/core/weights.py
hcai_models/expansion/__init__.py
hcai_models/expansion/keras/__init__.py
hcai_models/expansion/keras/layers.py
hcai_models/expansion/keras/losses.py
hcai_models/expansion/keras/preprocessing/__init__.py
hcai_models/expansion/keras/preprocessing/blaze_face_detector.py
hcai_models/expansion/keras/preprocessing/bounding_box_image_crop.py
hcai_models/expansion/keras/preprocessing/s3fd_detector.py
hcai_models/expansion/pytorch/__init__.py
hcai_models/expansion/pytorch/preprocessing/__init__.py
hcai_models/expansion/pytorch/preprocessing/pytorch_face_crop.py
hcai_models/models/__init__.py
hcai_models/models/audio/__init__.py
hcai_models/models/audio/soundnet/__init__.py
hcai_models/models/audio/soundnet/soundnet.py
hcai_models/models/audio/soundnet/weights.csv
hcai_models/models/feature/__init__.py
hcai_models/models/generative/__init__.py
hcai_models/models/generative/hcai_cycle_gan/__init__.py
hcai_models/models/generative/hcai_cycle_gan/classifier.py
hcai_models/models/generative/hcai_cycle_gan/cycle_gan.py
hcai_models/models/generative/hcai_cycle_gan/discriminator.py
hcai_models/models/generative/hcai_cycle_gan/generator.py
hcai_models/models/image/__init__.py
hcai_models/models/image/hcai_blaze_face/__init__.py
hcai_models/models/image/hcai_blaze_face/blaze_face.py
hcai_models/models/image/hcai_blaze_face/blaze_face_source.py
hcai_models/models/image/hcai_blaze_face/blaze_face_utils.py
hcai_models/models/image/hcai_blaze_face/weights.csv
hcai_models/models/image/hcai_efficient_net/__init__.py
hcai_models-0.1.1.dist-info/METADATA
hcai_models-0.1.1.dist-info/WHEEL
hcai_models-0.1.1.dist-info/top_level.txt
hcai_models-0.1.1.dist-info/RECORD
